tests/fixtures/trace_demo.sv
// A design built around one question: why is `out_data` the value it is?
//
// The waveform shows that it changes on some beats and not others, which is
// what a waveform can say. Why is provenance's job, and the path from
// `out_data` back to the edge of the design walks through every kind of answer
// the Trace view gives, in order:
//
//   out_data   assign                  combinational
//   staged     always_ff, guarded      register on clk, reset rst_n
//                                      — `in_data` is data, `gate` is a condition
//   gate       u_gate.allow            from an instance   -> go inside
//   allow      always_ff with a case   register, `case (mode)` and `if (want)`
//   want       a port of the child     from outside       -> go up
//   in_valid   a port of the top       the edge of the design
//
// `mode` decides whether the gate passes every beat, exactly one, or none, so
// the recording has stretches where data is held for a reason that is nowhere
// in `trace_demo` itself — it is two hops away, inside the child.

module trace_gate (
    input  logic       clk,
    input  logic       rst_n,
    input  logic       want,
    input  logic [1:0] mode,
    output logic       allow
);

    localparam logic [1:0] HOLD = 2'd0;
    localparam logic [1:0] PASS = 2'd1;
    localparam logic [1:0] ONCE = 2'd2;

    // Set once `ONCE` has let a beat through, so the second one is refused.
    logic used;

    always_ff @(posedge clk or negedge rst_n) begin
        if (!rst_n) begin
            allow <= 1'b0;
            used  <= 1'b0;
        end else begin
            case (mode)
                PASS: allow <= want;
                ONCE: begin
                    allow <= want && !used;
                    if (want) used <= 1'b1;
                end
                default: allow <= 1'b0;
            endcase
        end
    end

endmodule

module trace_demo (
    input  logic       clk,
    input  logic       rst_n,
    input  logic [7:0] in_data,
    input  logic       in_valid,
    input  logic [1:0] mode,
    output logic [7:0] out_data,
    output logic       out_valid
);

    logic [7:0] staged;
    logic       armed;
    logic       gate;

    trace_gate u_gate (
        .clk   (clk),
        .rst_n (rst_n),
        .want  (in_valid),
        .mode  (mode),
        .allow (gate)
    );

    always_ff @(posedge clk or negedge rst_n) begin
        if (!rst_n) begin
            staged <= 8'h00;
            armed  <= 1'b0;
        end else if (gate) begin
            staged <= in_data;
            armed  <= 1'b1;
        end
    end

    assign out_data  = staged;
    assign out_valid = armed && gate;

endmodule

tests/fixtures/waves/trace_demo.vcd
$version Generated by VerilatedVcd $end
$timescale 1ps $end
 $scope module $rootio $end
  $var wire 1 " clk $end
  $var wire 1 # rst_n $end
  $var wire 8 $ in_data [7:0] $end
  $var wire 1 % in_valid $end
  $var wire 2 & mode [1:0] $end
  $var wire 8 ' out_data [7:0] $end
  $var wire 1 ( out_valid $end
 $upscope $end
 $scope module trace_demo $end
  $var wire 1 ) clk $end
  $var wire 1 * rst_n $end
  $var wire 8 + in_data [7:0] $end
  $var wire 1 , in_valid $end
  $var wire 2 - mode [1:0] $end
  $var wire 8 . out_data [7:0] $end
  $var wire 1 / out_valid $end
  $var wire 8 0 staged [7:0] $end
  $var wire 1 1 armed $end
  $var wire 1 2 gate $end
  $scope module u_gate $end
   $var wire 1 3 clk $end
   $var wire 1 4 rst_n $end
   $var wire 1 5 want $end
   $var wire 2 6 mode [1:0] $end
   $var wire 1 7 allow $end
   $var wire 2 9 HOLD [1:0] $end
   $var wire 2 : PASS [1:0] $end
   $var wire 2 ; ONCE [1:0] $end
   $var wire 1 8 used $end
  $upscope $end
 $upscope $end
$enddefinitions $end


#0
1"
0#
b00000000 $
0%
b00 &
b00000000 '
0(
1)
0*
b00000000 +
0,
b00 -
b00000000 .
0/
b00000000 0
01
02
13
04
05
b00 6
07
08
b00 9
b01 :
b10 ;
#5000
0"
0)
03
#10000
1"
1)
13
#15000
0"
0)
03
#20000
1"
1)
13
#25000
0"
0)
03
#30000
1"
1)
13
#35000
0"
0)
03
#40000
1"
1#
1)
1*
13
14
#45000
0"
0)
03
#50000
1"
0#
1)
0*
13
04
#55000
0"
0)
03
#60000
1"
1)
13
#65000
0"
0)
03
#70000
1"
1)
13
#75000
0"
0)
03
#80000
1"
1)
13
#85000
0"
0)
03
#90000
1"
1#
b00010100 $
1%
b01 &
1)
1*
b00010100 +
1,
b01 -
13
14
15
b01 6
#95000
0"
0)
03
#100000
1"
b00010101 $
1)
b00010101 +
12
13
17
#105000
0"
0)
03
#110000
1"
b00010110 $
b00010101 '
1(
1)
b00010110 +
b00010101 .
1/
b00010101 0
11
13
#115000
0"
0)
03
#120000
1"
b00010111 $
b00010110 '
1)
b00010111 +
b00010110 .
b00010110 0
13
#125000
0"
0)
03
#130000
1"
b00011000 $
b00010111 '
1)
b00011000 +
b00010111 .
b00010111 0
13
#135000
0"
0)
03
#140000
1"
b00011001 $
b00011000 '
1)
b00011001 +
b00011000 .
b00011000 0
13
#145000
0"
0)
03
#150000
1"
b00011010 $
b00011001 '
1)
b00011010 +
b00011001 .
b00011001 0
13
#155000
0"
0)
03
#160000
1"
b00011011 $
b00011010 '
1)
b00011011 +
b00011010 .
b00011010 0
13
#165000
0"
0)
03
#170000
1"
b00011100 $
b10 &
b00011011 '
1)
b00011100 +
b10 -
b00011011 .
b00011011 0
13
b10 6
#175000
0"
0)
03
#180000
1"
b00011101 $
b00011100 '
1)
b00011101 +
b00011100 .
b00011100 0
13
18
#185000
0"
0)
03
#190000
1"
b00011110 $
b00011101 '
0(
1)
b00011110 +
b00011101 .
0/
b00011101 0
02
13
07
#195000
0"
0)
03
#200000
1"
b00011111 $
1)
b00011111 +
13
#205000
0"
0)
03
#210000
1"
b00100000 $
1)
b00100000 +
13
#215000
0"
0)
03
#220000
1"
b00100001 $
1)
b00100001 +
13
#225000
0"
0)
03
#230000
1"
b00100010 $
1)
b00100010 +
13
#235000
0"
0)
03
#240000
1"
b00100011 $
1)
b00100011 +
13
#245000
0"
0)
03
#250000
1"
b00100100 $
b00 &
1)
b00100100 +
b00 -
13
b00 6
#255000
0"
0)
03
#260000
1"
b00100101 $
1)
b00100101 +
13
#265000
0"
0)
03
#270000
1"
b00100110 $
1)
b00100110 +
13
#275000
0"
0)
03
#280000
1"
b00100111 $
1)
b00100111 +
13
#285000
0"
0)
03
#290000
1"
b00101000 $
1)
b00101000 +
13
#295000
0"
0)
03
#300000
1"
b00101001 $
1)
b00101001 +
13
#305000
0"
0)
03
#310000
1"
b00101010 $
1)
b00101010 +
13
#315000
0"
0)
03
#320000
1"
b00101011 $
1)
b00101011 +
13
